neso_utils/__init__.py
neso_utils/assessment_report/README.md
neso_utils/assessment_report/__init__.py
neso_utils/assessment_report/constants/__init__.py
neso_utils/assessment_report/constants/sparql.py
neso_utils/assessment_report/generator.py
neso_utils/assessment_report/kafka/__init__.py
neso_utils/assessment_report/kafka/metrics.py
neso_utils/assessment_report/utils/__init__.py
neso_utils/assessment_report/utils/dict.py
neso_utils/assessment_report/utils/sparql.py
neso_utils/schema_validation/README.md
neso_utils/schema_validation/__init__.py
neso_utils/schema_validation/detectors/__init__.py
neso_utils/schema_validation/detectors/ddl.py
neso_utils/schema_validation/detectors/ontology.py
neso_utils/schema_validation/detectors/shacl.py
neso_utils/schema_validation/injector.py
neso_utils/schema_validation/utils/__init__.py
neso_utils/schema_validation/utils/pandas.py
neso_utils/schema_validation/validator.py
neso_utils/synthetic_data_generator/README.md
neso_utils/synthetic_data_generator/__init__.py
neso_utils/synthetic_data_generator/configs/__init__.py
neso_utils/synthetic_data_generator/configs/constants.py
neso_utils/synthetic_data_generator/configs/mappers.py
neso_utils/synthetic_data_generator/generator/__init__.py
neso_utils/synthetic_data_generator/generator/engine.py
neso_utils/synthetic_data_generator/sampling/__init__.py
neso_utils/synthetic_data_generator/sampling/geojson.py
neso_utils/synthetic_data_generator/sampling/ttl.py
neso_utils/synthetic_data_generator/utils/__init__.py
neso_utils/synthetic_data_generator/utils/avro.py
neso_utils/synthetic_data_generator/utils/pandas.py
neso_utils/synthetic_data_generator/utils/triples.py
neso_utils-1.0.6.dist-info/WHEEL
neso_utils-1.0.6.dist-info/METADATA
neso_utils-1.0.6.dist-info/RECORD
