Metadata-Version: 2.1
Name: neso-utils
Version: 1.0.6
Summary: Library of utilities for NESO.
Author: Joao Nisa
Author-email: joao.nisa@mesh-ai.com
Requires-Python: >=3.10,<4.0
Classifier: Programming Language :: Python :: 3
Classifier: Programming Language :: Python :: 3.10
Classifier: Programming Language :: Python :: 3.11
Requires-Dist: fastavro (==1.9.1)
Requires-Dist: geopandas (==1.0.1)
Requires-Dist: jmxquery (==0.6.0)
Requires-Dist: numpy (==1.24.1)
Requires-Dist: pyshacl (==0.29.0)
Requires-Dist: randomname (==0.2.1)
Requires-Dist: rdflib (==7.1.1)
Requires-Dist: requests (==2.32.3)
Requires-Dist: setuptools (==68.2.2)
Requires-Dist: shapely (==2.0.6)
